gandalf_krmhd-0.2.0.dist-info/licenses/LICENSE
krmhd/__init__.py
krmhd/config.py
krmhd/diagnostics.py
krmhd/forcing.py
krmhd/hermite.py
krmhd/io.py
krmhd/physics.py
krmhd/py.typed
krmhd/spectral.py
krmhd/timestepping.py
krmhd/validation.py
gandalf_krmhd-0.2.0.dist-info/METADATA
gandalf_krmhd-0.2.0.dist-info/WHEEL
gandalf_krmhd-0.2.0.dist-info/top_level.txt
gandalf_krmhd-0.2.0.dist-info/RECORD
