Metadata-Version: 2.4
Name: gandalf-krmhd
Version: 0.2.0
Summary: Kinetic Reduced MHD (KRMHD) spectral solver for magnetized plasma turbulence
Author-email: anjor <anjor@umd.edu>
License: MIT
Project-URL: Homepage, https://github.com/anjor/gandalf
Project-URL: Repository, https://github.com/anjor/gandalf
Project-URL: Issues, https://github.com/anjor/gandalf/issues
Project-URL: Documentation, https://github.com/anjor/gandalf#readme
Project-URL: Changelog, https://github.com/anjor/gandalf/releases
Keywords: plasma physics,magnetohydrodynamics,MHD,turbulence,spectral methods,kinetic theory,astrophysics,JAX
Classifier: Development Status :: 3 - Alpha
Classifier: Intended Audience :: Science/Research
Classifier: License :: OSI Approved :: MIT License
Classifier: Programming Language :: Python :: 3
Classifier: Programming Language :: Python :: 3.10
Classifier: Programming Language :: Python :: 3.11
Classifier: Programming Language :: Python :: 3.12
Classifier: Topic :: Scientific/Engineering :: Physics
Classifier: Topic :: Scientific/Engineering :: Astronomy
Requires-Python: >=3.10
License-File: LICENSE
Requires-Dist: h5py>=3.11.0
Requires-Dist: jax>=0.4.20
Requires-Dist: matplotlib>=3.7.0
Requires-Dist: numpy>=1.24.0
Requires-Dist: pydantic>=2.0.0
Requires-Dist: pyyaml>=6.0.0
Requires-Dist: scipy>=1.10.0
Provides-Extra: metal
Requires-Dist: jax-metal>=0.0.4; extra == "metal"
Dynamic: license-file
